azure/mgmt/devcenter/__init__.py
azure/mgmt/devcenter/_configuration.py
azure/mgmt/devcenter/_dev_center_mgmt_client.py
azure/mgmt/devcenter/_patch.py
azure/mgmt/devcenter/_serialization.py
azure/mgmt/devcenter/_vendor.py
azure/mgmt/devcenter/_version.py
azure/mgmt/devcenter/py.typed
azure/mgmt/devcenter/aio/__init__.py
azure/mgmt/devcenter/aio/_configuration.py
azure/mgmt/devcenter/aio/_dev_center_mgmt_client.py
azure/mgmt/devcenter/aio/_patch.py
azure/mgmt/devcenter/aio/operations/__init__.py
azure/mgmt/devcenter/aio/operations/_attached_networks_operations.py
azure/mgmt/devcenter/aio/operations/_catalogs_operations.py
azure/mgmt/devcenter/aio/operations/_check_name_availability_operations.py
azure/mgmt/devcenter/aio/operations/_check_scoped_name_availability_operations.py
azure/mgmt/devcenter/aio/operations/_dev_box_definitions_operations.py
azure/mgmt/devcenter/aio/operations/_dev_centers_operations.py
azure/mgmt/devcenter/aio/operations/_environment_definitions_operations.py
azure/mgmt/devcenter/aio/operations/_environment_types_operations.py
azure/mgmt/devcenter/aio/operations/_galleries_operations.py
azure/mgmt/devcenter/aio/operations/_image_versions_operations.py
azure/mgmt/devcenter/aio/operations/_images_operations.py
azure/mgmt/devcenter/aio/operations/_network_connections_operations.py
azure/mgmt/devcenter/aio/operations/_operation_statuses_operations.py
azure/mgmt/devcenter/aio/operations/_operations.py
azure/mgmt/devcenter/aio/operations/_patch.py
azure/mgmt/devcenter/aio/operations/_pools_operations.py
azure/mgmt/devcenter/aio/operations/_project_allowed_environment_types_operations.py
azure/mgmt/devcenter/aio/operations/_project_catalog_environment_definitions_operations.py
azure/mgmt/devcenter/aio/operations/_project_catalogs_operations.py
azure/mgmt/devcenter/aio/operations/_project_environment_types_operations.py
azure/mgmt/devcenter/aio/operations/_projects_operations.py
azure/mgmt/devcenter/aio/operations/_schedules_operations.py
azure_mgmt_devcenter-1.1.0.dist-info/LICENSE
azure_mgmt_devcenter-1.1.0.dist-info/METADATA
azure_mgmt_devcenter-1.1.0.dist-info/WHEEL
azure_mgmt_devcenter-1.1.0.dist-info/top_level.txt
azure_mgmt_devcenter-1.1.0.dist-info/RECORD
